[
	{"name":"ATM Sign","value":"U+1F3E7"},
	{"name":"Litter in Bin Sign","value":"U+1F6AE"},
	{"name":"Potable Water","value":"U+1F6B0"},
	{"name":"Wheelchair Symbol","value":"U+267F"},
	{"name":"Men’s Room","value":"U+1F6B9"},
	{"name":"Women’s Room","value":"U+1F6BA"},
	{"name":"Restroom","value":"U+1F6BB"},
	{"name":"Baby Symbol","value":"U+1F6BC"},
	{"name":"Water Closet","value":"U+1F6BE"},
	{"name":"Passport Control","value":"U+1F6C2"},
	{"name":"Customs","value":"U+1F6C3"},
	{"name":"Baggage Claim","value":"U+1F6C4"},
	{"name":"Left Luggage","value":"U+1F6C5"},
	{"name":"Warning","value":"U+26A0"},
	{"name":"Children Crossing","value":"U+1F6B8"},
	{"name":"No Entry","value":"U+26D4"},
	{"name":"Prohibited","value":"U+1F6AB"},
	{"name":"No Bicycles","value":"U+1F6B3"},
	{"name":"No Smoking","value":"U+1F6AD"},
	{"name":"No Littering","value":"U+1F6AF"},
	{"name":"Non-Potable Water","value":"U+1F6B1"},
	{"name":"No Pedestrians","value":"U+1F6B7"},
	{"name":"No Mobile Phones","value":"U+1F4F5"},
	{"name":"No One Under Eighteen","value":"U+1F51E"},
	{"name":"Radioactive","value":"U+2622"},
	{"name":"Biohazard","value":"U+2623"},
	{"name":"Up Arrow","value":"U+2B06"},
	{"name":"Up-Right Arrow","value":"U+2197"},
	{"name":"Right Arrow","value":"U+27A1"},
	{"name":"Down-Right Arrow","value":"U+2198"},
	{"name":"Down Arrow","value":"U+2B07"},
	{"name":"Down-Left Arrow","value":"U+2199"},
	{"name":"Left Arrow","value":"U+2B05"},
	{"name":"Up-Left Arrow","value":"U+2196"},
	{"name":"Up-Down Arrow","value":"U+2195"},
	{"name":"Left-Right Arrow","value":"U+2194"},
	{"name":"Right Arrow Curving Left","value":"U+21A9"},
	{"name":"Left Arrow Curving Right","value":"U+21AA"},
	{"name":"Right Arrow Curving Up","value":"U+2934"},
	{"name":"Right Arrow Curving Down","value":"U+2935"},
	{"name":"Clockwise Vertical Arrows","value":"U+1F503"},
	{"name":"Anticlockwise Arrows Button","value":"U+1F504"},
	{"name":"BACK Arrow","value":"U+1F519"},
	{"name":"END Arrow","value":"U+1F51A"},
	{"name":"ON! Arrow","value":"U+1F51B"},
	{"name":"SOON Arrow","value":"U+1F51C"},
	{"name":"TOP Arrow","value":"U+1F51D"},
	{"name":"Place of Worship","value":"U+1F6D0"},
	{"name":"Atom Symbol","value":"U+269B"},
	{"name":"Om","value":"U+1F549"},
	{"name":"Star of David","value":"U+2721"},
	{"name":"Wheel of Dharma","value":"U+2638"},
	{"name":"Yin Yang","value":"U+262F"},
	{"name":"Latin Cross","value":"U+271D"},
	{"name":"Orthodox Cross","value":"U+2626"},
	{"name":"Star and Crescent","value":"U+262A"},
	{"name":"Peace Symbol","value":"U+262E"},
	{"name":"Menorah","value":"U+1F54E"},
	{"name":"Dotted Six-Pointed Star","value":"U+1F52F"},
	{"name":"Aries","value":"U+2648"},
	{"name":"Taurus","value":"U+2649"},
	{"name":"Gemini","value":"U+264A"},
	{"name":"Cancer","value":"U+264B"},
	{"name":"Leo","value":"U+264C"},
	{"name":"Virgo","value":"U+264D"},
	{"name":"Libra","value":"U+264E"},
	{"name":"Scorpius","value":"U+264F"},
	{"name":"Sagittarius","value":"U+2650"},
	{"name":"Capricorn","value":"U+2651"},
	{"name":"Aquarius","value":"U+2652"},
	{"name":"Pisces","value":"U+2653"},
	{"name":"Ophiuchus","value":"U+26CE"},
	{"name":"Shuffle Tracks Button","value":"U+1F500"},
	{"name":"Repeat Button","value":"U+1F501"},
	{"name":"Repeat Single Button","value":"U+1F502"},
	{"name":"Play Button","value":"U+25B6"},
	{"name":"Fast-Forward Button","value":"U+23E9"},
	{"name":"Next Track Button","value":"U+23ED"},
	{"name":"Play Or Pause Button","value":"U+23EF"},
	{"name":"Reverse Button","value":"U+25C0"},
	{"name":"Fast Reverse Button","value":"U+23EA"},
	{"name":"Last Track Button","value":"U+23EE"},
	{"name":"Up Button","value":"U+1F53C"},
	{"name":"Fast Up Button","value":"U+23EB"},
	{"name":"Down Button","value":"U+1F53D"},
	{"name":"Fast Down Button","value":"U+23EC"},
	{"name":"Pause Button","value":"U+23F8"},
	{"name":"Stop Button","value":"U+23F9"},
	{"name":"Record Button","value":"U+23FA"},
	{"name":"Eject Button","value":"U+23CF"},
	{"name":"Cinema","value":"U+1F3A6"},
	{"name":"Dim Button","value":"U+1F505"},
	{"name":"Bright Button","value":"U+1F506"},
	{"name":"Antenna Bars","value":"U+1F4F6"},
	{"name":"Vibration Mode","value":"U+1F4F3"},
	{"name":"Mobile Phone Off","value":"U+1F4F4"},
	{"name":"Female Sign","value":"U+2640"},
	{"name":"Male Sign","value":"U+2642"},
	{"name":"Medical Symbol","value":"U+2695"},
	{"name":"Recycling Symbol","value":"U+267B"},
	{"name":"Fleur-De-Lis","value":"U+269C"},
	{"name":"Trident Emblem","value":"U+1F531"},
	{"name":"Name Badge","value":"U+1F4DB"},
	{"name":"Japanese Symbol for Beginner","value":"U+1F530"},
	{"name":"Heavy Large Circle","value":"U+2B55"},
	{"name":"White Heavy Check Mark","value":"U+2705"},
	{"name":"Ballot Box with Check","value":"U+2611"},
	{"name":"Heavy Check Mark","value":"U+2714"},
	{"name":"Heavy Multiplication X","value":"U+2716"},
	{"name":"Cross Mark","value":"U+274C"},
	{"name":"Cross Mark Button","value":"U+274E"},
	{"name":"Heavy Plus Sign","value":"U+2795"},
	{"name":"Heavy Minus Sign","value":"U+2796"},
	{"name":"Heavy Division Sign","value":"U+2797"},
	{"name":"Curly Loop","value":"U+27B0"},
	{"name":"Double Curly Loop","value":"U+27BF"},
	{"name":"Part Alternation Mark","value":"U+303D"},
	{"name":"Eight-Spoked Asterisk","value":"U+2733"},
	{"name":"Eight-Pointed Star","value":"U+2734"},
	{"name":"Sparkle","value":"U+2747"},
	{"name":"Double Exclamation Mark","value":"U+203C"},
	{"name":"Exclamation Question Mark","value":"U+2049"},
	{"name":"Question Mark","value":"U+2753"},
	{"name":"White Question Mark","value":"U+2754"},
	{"name":"White Exclamation Mark","value":"U+2755"},
	{"name":"Exclamation Mark","value":"U+2757"},
	{"name":"Wavy Dash","value":"U+3030"},
	{"name":"Copyright","value":"U+A9"},
	{"name":"Registered","value":"U+AE"},
	{"name":"Trade Mark","value":"U+2122"},
	{"name":"Keycap: \X{23}","value":"U+23 U+20E3"},
	{"name":"Keycap: *","value":"U+2A U+20E3"},
	{"name":"Keycap: 0","value":"U+30 U+20E3"},
	{"name":"Keycap: 1","value":"U+31 U+20E3"},
	{"name":"Keycap: 2","value":"U+32 U+20E3"},
	{"name":"Keycap: 3","value":"U+33 U+20E3"},
	{"name":"Keycap: 4","value":"U+34 U+20E3"},
	{"name":"Keycap: 5","value":"U+35 U+20E3"},
	{"name":"Keycap: 6","value":"U+36 U+20E3"},
	{"name":"Keycap: 7","value":"U+37 U+20E3"},
	{"name":"Keycap: 8","value":"U+38 U+20E3"},
	{"name":"Keycap: 9","value":"U+39 U+20E3"},
	{"name":"Keycap 10","value":"U+1F51F"},
	{"name":"Hundred Points","value":"U+1F4AF"},
	{"name":"Input Latin Uppercase","value":"U+1F520"},
	{"name":"Input Latin Lowercase","value":"U+1F521"},
	{"name":"Input Numbers","value":"U+1F522"},
	{"name":"Input Symbols","value":"U+1F523"},
	{"name":"Input Latin Letters","value":"U+1F524"},
	{"name":"A Button (blood type)","value":"U+1F170"},
	{"name":"AB Button (blood type)","value":"U+1F18E"},
	{"name":"B Button (blood type)","value":"U+1F171"},
	{"name":"CL Button","value":"U+1F191"},
	{"name":"COOL Button","value":"U+1F192"},
	{"name":"FREE Button","value":"U+1F193"},
	{"name":"Information","value":"U+2139"},
	{"name":"ID Button","value":"U+1F194"},
	{"name":"Circled M","value":"U+24C2"},
	{"name":"NEW Button","value":"U+1F195"},
	{"name":"NG Button","value":"U+1F196"},
	{"name":"O Button (blood type)","value":"U+1F17E"},
	{"name":"OK Button","value":"U+1F197"},
	{"name":"P Button","value":"U+1F17F"},
	{"name":"SOS Button","value":"U+1F198"},
	{"name":"UP! Button","value":"U+1F199"},
	{"name":"VS Button","value":"U+1F19A"},
	{"name":"Japanese “Here” Button","value":"U+1F201"},
	{"name":"Japanese “Service Charge” Button","value":"U+1F202"},
	{"name":"Japanese “Monthly Amount” Button","value":"U+1F237"},
	{"name":"Japanese “Not Free of Charge” Button","value":"U+1F236"},
	{"name":"Japanese “Reserved” Button","value":"U+1F22F"},
	{"name":"Japanese “Bargain” Button","value":"U+1F250"},
	{"name":"Japanese “Discount” Button","value":"U+1F239"},
	{"name":"Japanese “Free of Charge” Button","value":"U+1F21A"},
	{"name":"Japanese “Prohibited” Button","value":"U+1F232"},
	{"name":"Japanese “Acceptable” Button","value":"U+1F251"},
	{"name":"Japanese “Application” Button","value":"U+1F238"},
	{"name":"Japanese “Passing Grade” Button","value":"U+1F234"},
	{"name":"Japanese “Vacancy” Button","value":"U+1F233"},
	{"name":"Japanese “Congratulations” Button","value":"U+3297"},
	{"name":"Japanese “Secret” Button","value":"U+3299"},
	{"name":"Japanese “Open for Business” Button","value":"U+1F23A"},
	{"name":"Japanese “No Vacancy” Button","value":"U+1F235"},
	{"name":"Black Small Square","value":"U+25AA"},
	{"name":"White Small Square","value":"U+25AB"},
	{"name":"White Medium Square","value":"U+25FB"},
	{"name":"Black Medium Square","value":"U+25FC"},
	{"name":"White Medium-Small Square","value":"U+25FD"},
	{"name":"Black Medium-Small Square","value":"U+25FE"},
	{"name":"Black Large Square","value":"U+2B1B"},
	{"name":"White Large Square","value":"U+2B1C"},
	{"name":"Large Orange Diamond","value":"U+1F536"},
	{"name":"Large Blue Diamond","value":"U+1F537"},
	{"name":"Small Orange Diamond","value":"U+1F538"},
	{"name":"Small Blue Diamond","value":"U+1F539"},
	{"name":"Red Triangle Pointed Up","value":"U+1F53A"},
	{"name":"Red Triangle Pointed Down","value":"U+1F53B"},
	{"name":"Diamond with a Dot","value":"U+1F4A0"},
	{"name":"Radio Button","value":"U+1F518"},
	{"name":"Black Square Button","value":"U+1F532"},
	{"name":"White Square Button","value":"U+1F533"},
	{"name":"White Circle","value":"U+26AA"},
	{"name":"Black Circle","value":"U+26AB"},
	{"name":"Red Circle","value":"U+1F534"},
	{"name":"Blue Circle","value":"U+1F535"}
]